[{"id": 211, "tmima": "Μηχανολόγων Μηχανικών", "sxoli": "ΑΡΙΣΤΟΤΕΛΕΙΟ ΠΑΝΕΠΙΣΤΗΜΙΟ ΘΕΣΣΑΛΟΝΙΚΗΣ (ΑΠΘ)", "extraInfo": null, "tipos": "ΑΕΙ", "poli": "Θεσσαλονίκη", "ebe": {}, "moria": 16812}, {"id": 261, "tmima": "Φυσικής", "sxoli": "ΠΑΝΕΠΙΣΤΗΜΙΟ ΚΡΗΤΗΣ", "extraInfo": null, "tipos": "ΑΕΙ", "poli": "Ηράκλειο", "ebe": {}, "moria": 15911}, {"id": 401, "tmima": "Επιστήμης Φυσικής Αγωγής και Αθλητισμού", "sxoli": "ΕΘΝΙΚΟ & ΚΑΠΟΔΙΣΤΡΙΑΚΟ ΠΑΝΕΠΙΣΤΗΜΙΟ ΑΘΗΝΩΝ (ΕΚΠΑ)", "extraInfo": "Εξέταση σε αγωνίσματα", "tipos": "ΑΕΙ", "poli": "Αθήνα", "ebe": {}, "moria": 14496}, {"id": 233, "tmima": "Αρχιτεκτόνων Μηχανικών", "sxoli": "ΑΡΙΣΤΟΤΕΛΕΙΟ ΠΑΝΕΠΙΣΤΗΜΙΟ ΘΕΣΣΑΛΟΝΙΚΗΣ (ΑΠΘ)", "extraInfo": "Ειδικά μαθήματα: Ελεύθερο και Γραμμικό Σχέδιο", "tipos": "ΑΕΙ", "poli": "Θεσσαλονίκη", "ebe": {}, "moria": 14060}, {"id": 328, "tmima": "Επιστήμης Τροφίμων και Διατροφής του Ανθρώπου", "sxoli": "ΓΕΩΠΟΝΙΚΟ ΠΑΝΕΠΙΣΤΗΜΙΟ ΑΘΗΝΩΝ", "extraInfo": null, "tipos": "ΑΕΙ", "poli": "Αθήνα", "ebe": {}, "moria": 13504}, {"id": 234, "tmima": "Αρχιτεκτόνων Μηχανικών", "sxoli": "ΔΗΜΟΚΡΙΤΕΙΟ ΠΑΝΕΠΙΣΤΗΜΙΟ ΘΡΑΚΗΣ (ΔΠΘ)", "extraInfo": "Ειδικά μαθήματα: Ελεύθερο και Γραμμικό Σχέδιο", "tipos": "ΑΕΙ", "poli": "Ξάνθη", "ebe": {}, "moria": 12485}, {"id": 231, "tmima": "Αρχιτεκτόνων Μηχανικών", "sxoli": "ΕΘΝΙΚΟ ΜΕΤΣΟΒΙΟ ΠΟΛΥΤΕΧΝΕΙΟ (ΕΜΠ)", "extraInfo": "Ειδικά μαθήματα: Ελεύθερο και Γραμμικό Σχέδιο", "tipos": "ΑΕΙ", "poli": "Αθήνα", "ebe": {}, "moria": 11967}, {"id": 168, "tmima": "Θεάτρου", "sxoli": "ΑΡΙΣΤΟΤΕΛΕΙΟ ΠΑΝΕΠΙΣΤΗΜΙΟ ΘΕΣΣΑΛΟΝΙΚΗΣ (ΑΠΘ)", "extraInfo": null, "tipos": "ΑΕΙ", "poli": "Θεσσαλονίκη", "ebe": {}, "moria": 11892}, {"id": 403, "tmima": "Επιστήμης Φυσικής Αγωγής και Αθλητισμού", "sxoli": "ΑΡΙΣΤΟΤΕΛΕΙΟ ΠΑΝΕΠΙΣΤΗΜΙΟ ΘΕΣΣΑΛΟΝΙΚΗΣ (ΑΠΘ)", "extraInfo": "Εξέταση σε αγωνίσματα", "tipos": "ΑΕΙ", "poli": "Θεσσαλονίκη", "ebe": {}, "moria": 11885}, {"id": 477, "tmima": "Εκπαιδευτικών Μηχανολόγων Μηχανικών", "sxoli": "ΑΝΩΤΑΤΗ ΣΧΟΛΗ ΠΑΙΔΑΓΩΓΙΚΗΣ & ΤΕΧΝΟΛΟΓΙΚΗΣ ΕΚΠΑΙΔΕΥΣΗΣ (ΑΣΠΑΙΤΕ)", "extraInfo": null, "tipos": "ΑΣΠΑΙΤΕ", "poli": "Αθήνα", "ebe": {}, "moria": 11881}, {"id": 279, "tmima": "Βιολογίας", "sxoli": "ΑΡΙΣΤΟΤΕΛΕΙΟ ΠΑΝΕΠΙΣΤΗΜΙΟ ΘΕΣΣΑΛΟΝΙΚΗΣ (ΑΠΘ)", "extraInfo": null, "tipos": "ΑΕΙ", "poli": "Θεσσαλονίκη", "ebe": {}, "moria": 11802}, {"id": 277, "tmima": "Βιολογίας", "sxoli": "ΕΘΝΙΚΟ & ΚΑΠΟΔΙΣΤΡΙΑΚΟ ΠΑΝΕΠΙΣΤΗΜΙΟ ΑΘΗΝΩΝ (ΕΚΠΑ)", "extraInfo": null, "tipos": "ΑΕΙ", "poli": "Αθήνα", "ebe": {}, "moria": 11517}, {"id": 409, "tmima": "Μουσικής Επιστήμης και Τέχνης", "sxoli": "ΠΑΝΕΠΙΣΤΗΜΙΟ ΜΑΚΕΔΟΝΙΑΣ (ΠΑΜΑΚ)", "extraInfo": "Ειδικά Μαθήματα: Μουσική Εκτέλεση και Ερμηνεία, Μουσική Αντίληψη και ΓνώσηΕιδική διαδικασία εισαγωγής χωρίς ΕΒΕ και Συντελεστές Βαρύτητας", "tipos": "ΑΕΙ", "poli": "Θεσσαλονίκη", "ebe": {}, "moria": 11498}, {"id": 282, "tmima": "Βιολογίας", "sxoli": "ΠΑΝΕΠΙΣΤΗΜΙΟ ΚΡΗΤΗΣ", "extraInfo": null, "tipos": "ΑΕΙ", "poli": "Ηράκλειο", "ebe": {}, "moria": 10827}, {"id": 219, "tmima": "Ηλεκτρολόγων Μηχανικών και Μηχανικών Υπολογιστών", "sxoli": "ΑΡΙΣΤΟΤΕΛΕΙΟ ΠΑΝΕΠΙΣΤΗΜΙΟ ΘΕΣΣΑΛΟΝΙΚΗΣ (ΑΠΘ)", "extraInfo": null, "tipos": "ΑΕΙ", "poli": "Θεσσαλονίκη", "ebe": {}, "moria": 10725}, {"id": 173, "tmima": "Ιστορίας και Φιλοσοφίας της Επιστήμης", "sxoli": "ΕΘΝΙΚΟ & ΚΑΠΟΔΙΣΤΡΙΑΚΟ ΠΑΝΕΠΙΣΤΗΜΙΟ ΑΘΗΝΩΝ (ΕΚΠΑ)", "extraInfo": null, "tipos": "ΑΕΙ", "poli": "Αθήνα", "ebe": {}, "moria": 10673}, {"id": 284, "tmima": "Βιοχημείας και Βιοτεχνολογίας", "sxoli": "ΠΑΝΕΠΙΣΤΗΜΙΟ ΘΕΣΣΑΛΙΑΣ", "extraInfo": null, "tipos": "ΑΕΙ", "poli": "Λάρισα", "ebe": {}, "moria": 10527}, {"id": 281, "tmima": "Βιολογίας", "sxoli": "ΠΑΝΕΠΙΣΤΗΜΙΟ ΠΑΤΡΩΝ", "extraInfo": null, "tipos": "ΑΕΙ", "poli": "Πάτρα", "ebe": {}, "moria": 10064}, {"id": 237, "tmima": "Χημικών Μηχανικών", "sxoli": "ΑΡΙΣΤΟΤΕΛΕΙΟ ΠΑΝΕΠΙΣΤΗΜΙΟ ΘΕΣΣΑΛΟΝΙΚΗΣ (ΑΠΘ)", "extraInfo": null, "tipos": "ΑΕΙ", "poli": "Θεσσαλονίκη", "ebe": {}, "moria": 9981}, {"id": 363, "tmima": "Μηχανικών Χωροταξίας και Ανάπτυξης", "sxoli": "ΑΡΙΣΤΟΤΕΛΕΙΟ ΠΑΝΕΠΙΣΤΗΜΙΟ ΘΕΣΣΑΛΟΝΙΚΗΣ (ΑΠΘ)", "extraInfo": null, "tipos": "ΑΕΙ", "poli": "Θεσσαλονίκη", "ebe": {}, "moria": 9962}, {"id": 263, "tmima": "Χημείας", "sxoli": "ΕΘΝΙΚΟ & ΚΑΠΟΔΙΣΤΡΙΑΚΟ ΠΑΝΕΠΙΣΤΗΜΙΟ ΑΘΗΝΩΝ (ΕΚΠΑ)", "extraInfo": null, "tipos": "ΑΕΙ", "poli": "Αθήνα", "ebe": {}, "moria": 9543}, {"id": 205, "tmima": "Πολιτικών Μηχανικών", "sxoli": "ΠΑΝΕΠΙΣΤΗΜΙΟ ΠΑΤΡΩΝ", "extraInfo": null, "tipos": "ΑΕΙ", "poli": "Πάτρα", "ebe": {}, "moria": 9391}, {"id": 163, "tmima": "Κινηματογράφου", "sxoli": "ΑΡΙΣΤΟΤΕΛΕΙΟ ΠΑΝΕΠΙΣΤΗΜΙΟ ΘΕΣΣΑΛΟΝΙΚΗΣ (ΑΠΘ)", "extraInfo": null, "tipos": "ΑΕΙ", "poli": "Θεσσαλονίκη", "ebe": {}, "moria": 9234}, {"id": 229, "tmima": "Ναυπηγών Μηχανολόγων Μηχανικών", "sxoli": "ΕΘΝΙΚΟ ΜΕΤΣΟΒΙΟ ΠΟΛΥΤΕΧΝΕΙΟ (ΕΜΠ)", "extraInfo": null, "tipos": "ΑΕΙ", "poli": "Αθήνα", "ebe": {}, "moria": 9166}, {"id": 209, "tmima": "Μηχανολόγων Μηχανικών", "sxoli": "ΕΘΝΙΚΟ ΜΕΤΣΟΒΙΟ ΠΟΛΥΤΕΧΝΕΙΟ (ΕΜΠ)", "extraInfo": null, "tipos": "ΑΕΙ", "poli": "Αθήνα", "ebe": {}, "moria": 9062}, {"id": 333, "tmima": "Πληροφορικής", "sxoli": "ΟΙΚΟΝΟΜΙΚΟ ΠΑΝΕΠΙΣΤΗΜΙΟ ΑΘΗΝΩΝ (ΟΠΑ)", "extraInfo": null, "tipos": "ΑΕΙ", "poli": "Αθήνα", "ebe": {}, "moria": 8803}, {"id": 402, "tmima": "Επιστήμης Φυσικής Αγωγής και Αθλητισμού", "sxoli": "ΑΡΙΣΤΟΤΕΛΕΙΟ ΠΑΝΕΠΙΣΤΗΜΙΟ ΘΕΣΣΑΛΟΝΙΚΗΣ (ΑΠΘ)", "extraInfo": "Εξέταση σε αγωνίσματα", "tipos": "ΑΕΙ", "poli": "Σέρρες", "ebe": {}, "moria": 8713}, {"id": 817, "tmima": "Σχολή Πλοιάρχων", "sxoli": "ΑΚΑΔΗΜΙΕΣ ΕΜΠΟΡΙΚΟΥ ΝΑΥΤΙΚΟΥ (ΑΕΝ)", "extraInfo": "Ισχύουν επιπλέον προϋποθέσεις", "tipos": "ΕΜΠΟΡΙΚΟ ΝΑΥΤΙΚΟ", "poli": "(μη προσδιορισμένη)", "ebe": {}, "moria": 8708}, {"id": 323, "tmima": "Επιστήμης Φυτικής Παραγωγής", "sxoli": "ΓΕΩΠΟΝΙΚΟ ΠΑΝΕΠΙΣΤΗΜΙΟ ΑΘΗΝΩΝ", "extraInfo": null, "tipos": "ΑΕΙ", "poli": "Αθήνα", "ebe": {}, "moria": 8694}, {"id": 325, "tmima": "Βιοτεχνολογίας", "sxoli": "ΓΕΩΠΟΝΙΚΟ ΠΑΝΕΠΙΣΤΗΜΙΟ ΑΘΗΝΩΝ", "extraInfo": null, "tipos": "ΑΕΙ", "poli": "Αθήνα", "ebe": {}, "moria": 8516}, {"id": 273, "tmima": "Γεωπονίας", "sxoli": "ΑΡΙΣΤΟΤΕΛΕΙΟ ΠΑΝΕΠΙΣΤΗΜΙΟ ΘΕΣΣΑΛΟΝΙΚΗΣ (ΑΠΘ)", "extraInfo": null, "tipos": "ΑΕΙ", "poli": "Θεσσαλονίκη", "ebe": {}, "moria": 8509}, {"id": 217, "tmima": "Ηλεκτρολόγων Μηχανικών και Μηχανικών Υπολογιστών", "sxoli": "ΕΘΝΙΚΟ ΜΕΤΣΟΒΙΟ ΠΟΛΥΤΕΧΝΕΙΟ (ΕΜΠ)", "extraInfo": null, "tipos": "ΑΕΙ", "poli": "Αθήνα", "ebe": {}, "moria": 8432}, {"id": 339, "tmima": "Πληροφορικής", "sxoli": "ΠΑΝΕΠΙΣΤΗΜΙΟ ΠΕΙΡΑΙΑ", "extraInfo": null, "tipos": "ΑΕΙ", "poli": "Πειραιάς", "ebe": {}, "moria": 8245}, {"id": 227, "tmima": "Αγρονόμων και Τοπογράφων Μηχανικών", "sxoli": "ΑΡΙΣΤΟΤΕΛΕΙΟ ΠΑΝΕΠΙΣΤΗΜΙΟ ΘΕΣΣΑΛΟΝΙΚΗΣ (ΑΠΘ)", "extraInfo": null, "tipos": "ΑΕΙ", "poli": "Θεσσαλονίκη", "ebe": {}, "moria": 8200}, {"id": 412, "tmima": "Πληροφορικής και Τηλεματικής", "sxoli": "ΧΑΡΟΚΟΠΕΙΟ ΠΑΝΕΠΙΣΤΗΜΙΟ", "extraInfo": null, "tipos": "ΑΕΙ", "poli": "Αθήνα", "ebe": {}, "moria": 8169}, {"id": 218, "tmima": "Στατιστικής και Αναλογιστικών - Χρηματοοικονομικών Μαθηματικών", "sxoli": "ΠΑΝΕΠΙΣΤΗΜΙΟ ΑΙΓΑΙΟΥ", "extraInfo": null, "tipos": "ΑΕΙ", "poli": "Σάμος", "ebe": {}, "moria": 8099}, {"id": 324, "tmima": "Επιστήμης Ζωικής Παραγωγής", "sxoli": "ΓΕΩΠΟΝΙΚΟ ΠΑΝΕΠΙΣΤΗΜΙΟ ΑΘΗΝΩΝ", "extraInfo": null, "tipos": "ΑΕΙ", "poli": "Αθήνα", "ebe": {}, "moria": 7912}, {"id": 758, "tmima": "Τεχνολόγων Γεωπόνων", "sxoli": "Τ.Ε.Ι. ΚΡΗΤΗΣ", "extraInfo": "(Δεν υπάρχει στο Μηχανογραφικό του 2022)", "tipos": "ΤΕΙ", "poli": "Ηράκλειο", "ebe": {}, "moria": 7845}, {"id": 330, "tmima": "Πληροφορικής και Τηλεπικοινωνιών", "sxoli": "ΕΘΝΙΚΟ & ΚΑΠΟΔΙΣΤΡΙΑΚΟ ΠΑΝΕΠΙΣΤΗΜΙΟ ΑΘΗΝΩΝ (ΕΚΠΑ)", "extraInfo": null, "tipos": "ΑΕΙ", "poli": "Αθήνα", "ebe": {}, "moria": 7745}, {"id": 236, "tmima": "Αρχιτεκτόνων Μηχανικών", "sxoli": "ΠΑΝΕΠΙΣΤΗΜΙΟ ΘΕΣΣΑΛΙΑΣ", "extraInfo": "Ειδικά μαθήματα: Ελεύθερο και Γραμμικό Σχέδιο", "tipos": "ΑΕΙ", "poli": "Βόλος", "ebe": {}, "moria": 7691}, {"id": 405, "tmima": "Επιστήμης Φυσικής Αγωγής και Αθλητισμού", "sxoli": "ΠΑΝΕΠΙΣΤΗΜΙΟ ΘΕΣΣΑΛΙΑΣ", "extraInfo": "Εξέταση σε αγωνίσματα", "tipos": "ΑΕΙ", "poli": "Τρίκαλα", "ebe": {}, "moria": 7596}, {"id": 420, "tmima": "Πρόγραμμα Διαχείρισης Εκκλησιαστικών Κειμηλίων", "sxoli": "ΑΝΩΤΑΤΗ ΕΚΚΛΗΣΙΑΣΤΙΚΗ ΑΚΑΔΗΜΙΑ ΘΕΣΣΑΛΟΝΙΚΗΣ (ΑΕΑ)", "extraInfo": "Μόνο για Χριστιανούς Ορθόδοξους\n(Δεν υπάρχει στο Μηχανογραφικό του 2022)", "tipos": "ΕΚΚΛΗΣΙΑΣΤΙΚΕΣ ΑΚΑΔΗΜΙΕΣ", "poli": "Θεσσαλονίκη", "ebe": {}, "moria": 7524}, {"id": 338, "tmima": "Πληροφορικής", "sxoli": "ΑΡΙΣΤΟΤΕΛΕΙΟ ΠΑΝΕΠΙΣΤΗΜΙΟ ΘΕΣΣΑΛΟΝΙΚΗΣ (ΑΠΘ)", "extraInfo": null, "tipos": "ΑΕΙ", "poli": "Θεσσαλονίκη", "ebe": {}, "moria": 7362}, {"id": 246, "tmima": "Εφαρμοσμένων Μαθηματικών και Φυσικών Επιστημών", "sxoli": "ΕΘΝΙΚΟ ΜΕΤΣΟΒΙΟ ΠΟΛΥΤΕΧΝΕΙΟ (ΕΜΠ)", "extraInfo": null, "tipos": "ΑΕΙ", "poli": "Αθήνα", "ebe": {}, "moria": 7350}, {"id": 210, "tmima": "Μηχανολόγων Μηχανικών", "sxoli": "ΠΑΝΕΠΙΣΤΗΜΙΟ ΔΥΤΙΚΗΣ ΜΑΚΕΔΟΝΙΑΣ", "extraInfo": null, "tipos": "ΑΕΙ", "poli": "Κοζάνη", "ebe": {}, "moria": 7320}, {"id": 404, "tmima": "Επιστήμης Φυσικής Αγωγής και Αθλητισμού", "sxoli": "ΔΗΜΟΚΡΙΤΕΙΟ ΠΑΝΕΠΙΣΤΗΜΙΟ ΘΡΑΚΗΣ (ΔΠΘ)", "extraInfo": "Εξέταση σε αγωνίσματα", "tipos": "ΑΕΙ", "poli": "Κομοτηνή", "ebe": {}, "moria": 7280}, {"id": 285, "tmima": "Γεωλογίας", "sxoli": "ΑΡΙΣΤΟΤΕΛΕΙΟ ΠΑΝΕΠΙΣΤΗΜΙΟ ΘΕΣΣΑΛΟΝΙΚΗΣ (ΑΠΘ)", "extraInfo": null, "tipos": "ΑΕΙ", "poli": "Θεσσαλονίκη", "ebe": {}, "moria": 7224}, {"id": 290, "tmima": "Μοριακής Βιολογίας και Γενετικής", "sxoli": "ΔΗΜΟΚΡΙΤΕΙΟ ΠΑΝΕΠΙΣΤΗΜΙΟ ΘΡΑΚΗΣ (ΔΠΘ)", "extraInfo": null, "tipos": "ΑΕΙ", "poli": "Αλεξ/πολη", "ebe": {}, "moria": 7216}, {"id": 232, "tmima": "Αρχιτεκτόνων Μηχανικών", "sxoli": "ΠΑΝΕΠΙΣΤΗΜΙΟ ΠΑΤΡΩΝ", "extraInfo": "Ειδικά μαθήματα: Ελεύθερο και Γραμμικό Σχέδιο", "tipos": "ΑΕΙ", "poli": "Πάτρα", "ebe": {}, "moria": 7186}, {"id": 818, "tmima": "Σχολή Μηχανικών", "sxoli": "ΑΚΑΔΗΜΙΕΣ ΕΜΠΟΡΙΚΟΥ ΝΑΥΤΙΚΟΥ (ΑΕΝ)", "extraInfo": "Ισχύουν επιπλέον προϋποθέσεις", "tipos": "ΕΜΠΟΡΙΚΟ ΝΑΥΤΙΚΟ", "poli": "(μη προσδιορισμένη)", "ebe": {}, "moria": 7154}, {"id": 267, "tmima": "Χημείας", "sxoli": "ΠΑΝΕΠΙΣΤΗΜΙΟ ΠΑΤΡΩΝ", "extraInfo": null, "tipos": "ΑΕΙ", "poli": "Πάτρα", "ebe": {}, "moria": 7137}, {"id": 356, "tmima": "Γεωγραφίας", "sxoli": "ΧΑΡΟΚΟΠΕΙΟ ΠΑΝΕΠΙΣΤΗΜΙΟ", "extraInfo": null, "tipos": "ΑΕΙ", "poli": "Αθήνα", "ebe": {}, "moria": 6997}, {"id": 720, "tmima": "Μηχανικών Αυτοματισμού ΤΕ", "sxoli": "ΑΛΕΞΑΝΔΡΕΙΟ Τ.Ε.Ι. ΘΕΣΣΑΛΟΝΙΚΗΣ", "extraInfo": "(Δεν υπάρχει στο Μηχανογραφικό του 2022)", "tipos": "ΤΕΙ", "poli": "Θεσσαλονίκη", "ebe": {}, "moria": 6905}, {"id": 335, "tmima": "Εφαρμοσμένης Πληροφορικής", "sxoli": "ΠΑΝΕΠΙΣΤΗΜΙΟ ΜΑΚΕΔΟΝΙΑΣ (ΠΑΜΑΚ)", "extraInfo": "(Δεν υπάρχει στο Μηχανογραφικό του 2022)", "tipos": "ΑΕΙ", "poli": "Θεσσαλονίκη", "ebe": {}, "moria": 6863}, {"id": 275, "tmima": "Δασολογίας και Φυσικού Περιβάλλοντος", "sxoli": "ΑΡΙΣΤΟΤΕΛΕΙΟ ΠΑΝΕΠΙΣΤΗΜΙΟ ΘΕΣΣΑΛΟΝΙΚΗΣ (ΑΠΘ)", "extraInfo": null, "tipos": "ΑΕΙ", "poli": "Θεσσαλονίκη", "ebe": {}, "moria": 6846}, {"id": 696, "tmima": "Λαικής και Παραδοσιακής Μουσικής", "sxoli": "Τ.Ε.Ι. ΗΠΕΙΡΟΥ", "extraInfo": "Ισχύουν επιπλέον προϋποθέσεις\n(Δεν υπάρχει στο Μηχανογραφικό του 2022)", "tipos": "ΤΕΙ", "poli": "Άρτα", "ebe": {}, "moria": 6653}, {"id": 522, "tmima": "Σχεδιασμού και Τεχνολογίας Ξύλου και Επίπλου ΤΕ", "sxoli": "Τ.Ε.Ι. ΘΕΣΣΑΛΙΑΣ", "extraInfo": "(Δεν υπάρχει στο Μηχανογραφικό του 2022)", "tipos": "ΤΕΙ", "poli": "Καρδίτσα", "ebe": {}, "moria": 6652}, {"id": 201, "tmima": "Πολιτικών Μηχανικών", "sxoli": "ΕΘΝΙΚΟ ΜΕΤΣΟΒΙΟ ΠΟΛΥΤΕΧΝΕΙΟ (ΕΜΠ)", "extraInfo": null, "tipos": "ΑΕΙ", "poli": "Αθήνα", "ebe": {}, "moria": 6644}, {"id": 262, "tmima": "Ψηφιακών Συστημάτων", "sxoli": "ΠΑΝΕΠΙΣΤΗΜΙΟ ΠΕΙΡΑΙΑ", "extraInfo": null, "tipos": "ΑΕΙ", "poli": "Πειραιάς", "ebe": {}, "moria": 6619}, {"id": 241, "tmima": "Μεταλλειολόγων - Μεταλλουργών Μηχανικών", "sxoli": "ΕΘΝΙΚΟ ΜΕΤΣΟΒΙΟ ΠΟΛΥΤΕΧΝΕΙΟ (ΕΜΠ)", "extraInfo": null, "tipos": "ΑΕΙ", "poli": "Αθήνα", "ebe": {}, "moria": 6587}, {"id": 274, "tmima": "Γεωπονίας, Φυτικής Παραγωγής και Αγροτικού Περιβάλλοντος", "sxoli": "ΠΑΝΕΠΙΣΤΗΜΙΟ ΘΕΣΣΑΛΙΑΣ", "extraInfo": null, "tipos": "ΑΕΙ", "poli": "Βόλος", "ebe": {}, "moria": 6564}, {"id": 250, "tmima": "Επιστημών Της Θάλασσας", "sxoli": "ΠΑΝΕΠΙΣΤΗΜΙΟ ΑΙΓΑΙΟΥ", "extraInfo": "(Δεν υπάρχει στο Μηχανογραφικό του 2022)", "tipos": "ΑΕΙ", "poli": "Μυτιλήνη", "ebe": {}, "moria": 6548}, {"id": 203, "tmima": "Πολιτικών Μηχανικών", "sxoli": "ΑΡΙΣΤΟΤΕΛΕΙΟ ΠΑΝΕΠΙΣΤΗΜΙΟ ΘΕΣΣΑΛΟΝΙΚΗΣ (ΑΠΘ)", "extraInfo": null, "tipos": "ΑΕΙ", "poli": "Θεσσαλονίκη", "ebe": {}, "moria": 6457}, {"id": 276, "tmima": "Περιβάλλοντος", "sxoli": "ΠΑΝΕΠΙΣΤΗΜΙΟ ΑΙΓΑΙΟΥ", "extraInfo": null, "tipos": "ΑΕΙ", "poli": "Μυτιλήνη", "ebe": {}, "moria": 6420}, {"id": 518, "tmima": "Φωτογραφίας & Οπτικοακουστικών", "sxoli": "Τ.Ε.Ι. ΑΘΗΝΑΣ", "extraInfo": "(Δεν υπάρχει στο Μηχανογραφικό του 2022)", "tipos": "ΤΕΙ", "poli": "Αθήνα", "ebe": {}, "moria": 6376}, {"id": 245, "tmima": "Μαθηματικών", "sxoli": "ΑΡΙΣΤΟΤΕΛΕΙΟ ΠΑΝΕΠΙΣΤΗΜΙΟ ΘΕΣΣΑΛΟΝΙΚΗΣ (ΑΠΘ)", "extraInfo": null, "tipos": "ΑΕΙ", "poli": "Θεσσαλονίκη", "ebe": {}, "moria": 6345}, {"id": 480, "tmima": "Μηχανικών Βιοϊατρικής Τεχνολογίας ΤΕ", "sxoli": "Τ.Ε.Ι. ΑΘΗΝΑΣ", "extraInfo": "(Δεν υπάρχει στο Μηχανογραφικό του 2022)", "tipos": "ΤΕΙ", "poli": "Αθήνα", "ebe": {}, "moria": 6292}, {"id": 776, "tmima": "Εκπαιδευτικών Πολιτικών Μηχανικών", "sxoli": "ΑΝΩΤΑΤΗ ΣΧΟΛΗ ΠΑΙΔΑΓΩΓΙΚΗΣ & ΤΕΧΝΟΛΟΓΙΚΗΣ ΕΚΠΑΙΔΕΥΣΗΣ (ΑΣΠΑΙΤΕ)", "extraInfo": null, "tipos": "ΑΣΠΑΙΤΕ", "poli": "Αθήνα", "ebe": {}, "moria": 6140}, {"id": 716, "tmima": "Τεχνολογίας Τροφίμων", "sxoli": "Τ.Ε.Ι. ΑΘΗΝΑΣ", "extraInfo": "(Δεν υπάρχει στο Μηχανογραφικό του 2022)", "tipos": "ΤΕΙ", "poli": "Αθήνα", "ebe": {}, "moria": 6100}, {"id": 371, "tmima": "Μηχανικών Πληροφορικής και Τηλεπικοινωνιών", "sxoli": "ΠΑΝΕΠΙΣΤΗΜΙΟ ΔΥΤΙΚΗΣ ΜΑΚΕΔΟΝΙΑΣ", "extraInfo": "(Δεν υπάρχει στο Μηχανογραφικό του 2022)", "tipos": "ΑΕΙ", "poli": "Κοζάνη", "ebe": {}, "moria": 6060}, {"id": 340, "tmima": "Μηχανικών Ηλεκτρονικών Υπολογιστών και Πληροφορικής", "sxoli": "ΠΑΝΕΠΙΣΤΗΜΙΟ ΙΩΑΝΝΙΝΩΝ", "extraInfo": null, "tipos": "ΑΕΙ", "poli": "Ιωάννινα", "ebe": {}, "moria": 6032}, {"id": 461, "tmima": "Μηχανολόγων Μηχανικών ΤΕ", "sxoli": "Τ.Ε.Ι. ΠΕΙΡΑΙΑ", "extraInfo": "(Δεν υπάρχει στο Μηχανογραφικό του 2022)", "tipos": "ΤΕΙ", "poli": "Πειραιάς", "ebe": {}, "moria": 6018}, {"id": 419, "tmima": "Πρόγραμμα Διαχείρισης Εκκλησιαστικών Κειμηλίων", "sxoli": "ΑΝΩΤΑΤΗ ΕΚΚΛΗΣΙΑΣΤΙΚΗ ΑΚΑΔΗΜΙΑ ΑΘΗΝΩΝ (ΑΕΑ)", "extraInfo": "Μόνο για Χριστιανούς Ορθόδοξους\n(Δεν υπάρχει στο Μηχανογραφικό του 2022)", "tipos": "ΕΚΚΛΗΣΙΑΣΤΙΚΕΣ ΑΚΑΔΗΜΙΕΣ", "poli": "Αθήνα", "ebe": {}, "moria": 5905}, {"id": 225, "tmima": "Αγρονόμων και Τοπογράφων Μηχανικών - Μηχανικών Γεωπληροφορικής", "sxoli": "ΕΘΝΙΚΟ ΜΕΤΣΟΒΙΟ ΠΟΛΥΤΕΧΝΕΙΟ (ΕΜΠ)", "extraInfo": null, "tipos": "ΑΕΙ", "poli": "Αθήνα", "ebe": {}, "moria": 5887}, {"id": 228, "tmima": "Μηχανικών Χωροταξίας, Πολεοδομίας και Περιφερειακής Ανάπτυξης", "sxoli": "ΠΑΝΕΠΙΣΤΗΜΙΟ ΘΕΣΣΑΛΙΑΣ", "extraInfo": null, "tipos": "ΑΕΙ", "poli": "Βόλος", "ebe": {}, "moria": 5870}, {"id": 216, "tmima": "Επιστήμης Υπολογιστών", "sxoli": "ΠΑΝΕΠΙΣΤΗΜΙΟ ΚΡΗΤΗΣ", "extraInfo": null, "tipos": "ΑΕΙ", "poli": "Ηράκλειο", "ebe": {}, "moria": 5852}, {"id": 516, "tmima": "Μηχανολόγων Οχημάτων ΤΕ", "sxoli": "ΑΛΕΞΑΝΔΡΕΙΟ Τ.Ε.Ι. ΘΕΣΣΑΛΟΝΙΚΗΣ", "extraInfo": "(Δεν υπάρχει στο Μηχανογραφικό του 2022)", "tipos": "ΤΕΙ", "poli": "Θεσσαλονίκη", "ebe": {}, "moria": 5848}, {"id": 270, "tmima": "Χημείας", "sxoli": "ΠΑΝΕΠΙΣΤΗΜΙΟ ΚΡΗΤΗΣ", "extraInfo": null, "tipos": "ΑΕΙ", "poli": "Ηράκλειο", "ebe": {}, "moria": 5805}, {"id": 367, "tmima": "Τεχνών Ήχου και Εικόνας", "sxoli": "ΙΟΝΙΟ ΠΑΝΕΠΙΣΤΗΜΙΟ", "extraInfo": null, "tipos": "ΑΕΙ", "poli": "Κέρκυρα", "ebe": {}, "moria": 5789}, {"id": 208, "tmima": "Πολιτικών Μηχανικών", "sxoli": "ΠΑΝΕΠΙΣΤΗΜΙΟ ΘΕΣΣΑΛΙΑΣ", "extraInfo": null, "tipos": "ΑΕΙ", "poli": "Βόλος", "ebe": {}, "moria": 5686}, {"id": 287, "tmima": "Γεωλογίας", "sxoli": "ΠΑΝΕΠΙΣΤΗΜΙΟ ΠΑΤΡΩΝ", "extraInfo": null, "tipos": "ΑΕΙ", "poli": "Πάτρα", "ebe": {}, "moria": 5476}, {"id": 511, "tmima": "Ναυπηγών Μηχανικών ΤΕ", "sxoli": "Τ.Ε.Ι. ΑΘΗΝΑΣ", "extraInfo": "(Δεν υπάρχει στο Μηχανογραφικό του 2022)", "tipos": "ΤΕΙ", "poli": "Αθήνα", "ebe": {}, "moria": 5388}, {"id": 445, "tmima": "Πολιτικών Μηχανικών ΤΕ", "sxoli": "Τ.Ε.Ι. ΠΕΙΡΑΙΑ", "extraInfo": "(Δεν υπάρχει στο Μηχανογραφικό του 2022)", "tipos": "ΤΕΙ", "poli": "Πειραιάς", "ebe": {}, "moria": 5378}, {"id": 280, "tmima": "Βιολογικών Εφαρμογών και Τεχνολογιών", "sxoli": "ΠΑΝΕΠΙΣΤΗΜΙΟ ΙΩΑΝΝΙΝΩΝ", "extraInfo": null, "tipos": "ΑΕΙ", "poli": "Ιωάννινα", "ebe": {}, "moria": 5344}, {"id": 235, "tmima": "Χημικών Μηχανικών", "sxoli": "ΕΘΝΙΚΟ ΜΕΤΣΟΒΙΟ ΠΟΛΥΤΕΧΝΕΙΟ (ΕΜΠ)", "extraInfo": null, "tipos": "ΑΕΙ", "poli": "Αθήνα", "ebe": {}, "moria": 5339}, {"id": 718, "tmima": "Οινολογίας & Τεχνολογίας Ποτών", "sxoli": "Τ.Ε.Ι. ΑΘΗΝΑΣ", "extraInfo": "(Δεν υπάρχει στο Μηχανογραφικό του 2022)", "tipos": "ΤΕΙ", "poli": "Αθήνα", "ebe": {}, "moria": 5330}, {"id": 752, "tmima": "Οινολογίας και Τεχνολογίας Ποτών", "sxoli": "Τ.Ε.Ι. ΑΝΑΤΟΛΙΚΗΣ ΜΑΚΕΔΟΝΙΑΣ & ΘΡΑΚΗΣ", "extraInfo": "(Δεν υπάρχει στο Μηχανογραφικό του 2022)", "tipos": "ΤΕΙ", "poli": "Δράμα", "ebe": {}, "moria": 5326}, {"id": 214, "tmima": "Χημικών Μηχανικών και Μηχανικών Περιβάλλοντος", "sxoli": "ΠΟΛΥΤΕΧΝΕΙΟ ΚΡΗΤΗΣ", "extraInfo": null, "tipos": "ΑΕΙ", "poli": "Χανιά", "ebe": {}, "moria": 5266}, {"id": 757, "tmima": "Τεχνολόγων Γεωπόνων", "sxoli": "Τ.Ε.Ι. ΗΠΕΙΡΟΥ", "extraInfo": "(Δεν υπάρχει στο Μηχανογραφικό του 2022)", "tipos": "ΤΕΙ", "poli": "Άρτα", "ebe": {}, "moria": 5180}, {"id": 360, "tmima": "Γεωπονίας, Ιχθυολογίας και Υδάτινου Περιβάλλοντος", "sxoli": "ΠΑΝΕΠΙΣΤΗΜΙΟ ΘΕΣΣΑΛΙΑΣ", "extraInfo": null, "tipos": "ΑΕΙ", "poli": "Βόλος", "ebe": {}, "moria": 5175}, {"id": 483, "tmima": "Ηλεκτρολόγων Μηχανικών ΤΕ", "sxoli": "Τ.Ε.Ι. ΠΕΙΡΑΙΑ", "extraInfo": "(Δεν υπάρχει στο Μηχανογραφικό του 2022)", "tipos": "ΤΕΙ", "poli": "Πειραιάς", "ebe": {}, "moria": 5116}, {"id": 223, "tmima": "Ηλεκτρολόγων Μηχανικών και Μηχανικών Υπολογιστών", "sxoli": "ΔΗΜΟΚΡΙΤΕΙΟ ΠΑΝΕΠΙΣΤΗΜΙΟ ΘΡΑΚΗΣ (ΔΠΘ)", "extraInfo": null, "tipos": "ΑΕΙ", "poli": "Ξάνθη", "ebe": {}, "moria": 5099}, {"id": 283, "tmima": "Γεωλογίας και Γεωπεριβάλλοντος", "sxoli": "ΕΘΝΙΚΟ & ΚΑΠΟΔΙΣΤΡΙΑΚΟ ΠΑΝΕΠΙΣΤΗΜΙΟ ΑΘΗΝΩΝ (ΕΚΠΑ)", "extraInfo": null, "tipos": "ΑΕΙ", "poli": "Αθήνα", "ebe": {}, "moria": 5034}, {"id": 212, "tmima": "Δασολογίας και Διαχείρισης Περιβάλλοντος και Φυσικών Πόρων", "sxoli": "ΔΗΜΟΚΡΙΤΕΙΟ ΠΑΝΕΠΙΣΤΗΜΙΟ ΘΡΑΚΗΣ (ΔΠΘ)", "extraInfo": null, "tipos": "ΑΕΙ", "poli": "Ορεστιάδα", "ebe": {}, "moria": 5024}, {"id": 336, "tmima": "Βιομηχανικής Διοίκησης και Τεχνολογίας", "sxoli": "ΠΑΝΕΠΙΣΤΗΜΙΟ ΠΕΙΡΑΙΑ", "extraInfo": null, "tipos": "ΑΕΙ", "poli": "Πειραιάς", "ebe": {}, "moria": 5000}, {"id": 557, "tmima": "Τεχνολόγων Γεωπόνων", "sxoli": "Τ.Ε.Ι. ΔΥΤΙΚΗΣ ΕΛΛΑΔΑΣ", "extraInfo": "(Δεν υπάρχει στο Μηχανογραφικό του 2022)", "tipos": "ΤΕΙ", "poli": "Αμαλιάδα", "ebe": {}, "moria": 4997}, {"id": 207, "tmima": "Πολιτικών Μηχανικών", "sxoli": "ΔΗΜΟΚΡΙΤΕΙΟ ΠΑΝΕΠΙΣΤΗΜΙΟ ΘΡΑΚΗΣ (ΔΠΘ)", "extraInfo": null, "tipos": "ΑΕΙ", "poli": "Ξάνθη", "ebe": {}, "moria": 4945}, {"id": 329, "tmima": "Στατιστικής", "sxoli": "ΟΙΚΟΝΟΜΙΚΟ ΠΑΝΕΠΙΣΤΗΜΙΟ ΑΘΗΝΩΝ (ΟΠΑ)", "extraInfo": null, "tipos": "ΑΕΙ", "poli": "Αθήνα", "ebe": {}, "moria": 4910}, {"id": 327, "tmima": "Αξιοποίησης Φυσικών Πόρων και Γεωργικής Μηχανικής", "sxoli": "ΓΕΩΠΟΝΙΚΟ ΠΑΝΕΠΙΣΤΗΜΙΟ ΑΘΗΝΩΝ", "extraInfo": null, "tipos": "ΑΕΙ", "poli": "Αθήνα", "ebe": {}, "moria": 4899}, {"id": 501, "tmima": "Ηλεκτρονικών Μηχανικών ΤΕ", "sxoli": "Τ.Ε.Ι. ΑΘΗΝΑΣ", "extraInfo": "(Δεν υπάρχει στο Μηχανογραφικό του 2022)", "tipos": "ΤΕΙ", "poli": "Αθήνα", "ebe": {}, "moria": 4883}, {"id": 759, "tmima": "Τεχνολόγων Γεωπόνων", "sxoli": "ΑΛΕΞΑΝΔΡΕΙΟ Τ.Ε.Ι. ΘΕΣΣΑΛΟΝΙΚΗΣ", "extraInfo": "(Δεν υπάρχει στο Μηχανογραφικό του 2022)", "tipos": "ΤΕΙ", "poli": "Θεσσαλονίκη", "ebe": {}, "moria": 4848}, {"id": 369, "tmima": "Πληροφορικής με Εφαρμογές στη Βιοϊατρική", "sxoli": "ΠΑΝΕΠΙΣΤΗΜΙΟ ΘΕΣΣΑΛΙΑΣ", "extraInfo": null, "tipos": "ΑΕΙ", "poli": "Λαμία", "ebe": {}, "moria": 4813}, {"id": 476, "tmima": "Μηχανικών Περιβάλλοντος", "sxoli": "ΔΗΜΟΚΡΙΤΕΙΟ ΠΑΝΕΠΙΣΤΗΜΙΟ ΘΡΑΚΗΣ (ΔΠΘ)", "extraInfo": null, "tipos": "ΑΕΙ", "poli": "Ξάνθη", "ebe": {}, "moria": 4812}, {"id": 767, "tmima": "Μηχανολόγων Μηχανικών ΤΕ", "sxoli": "Τ.Ε.Ι. ΚΡΗΤΗΣ", "extraInfo": "(Δεν υπάρχει στο Μηχανογραφικό του 2022)", "tipos": "ΤΕΙ", "poli": "Ηράκλειο", "ebe": {}, "moria": 4807}, {"id": 332, "tmima": "Μηχανολόγων Μηχανικών", "sxoli": "ΠΑΝΕΠΙΣΤΗΜΙΟ ΘΕΣΣΑΛΙΑΣ", "extraInfo": null, "tipos": "ΑΕΙ", "poli": "Βόλος", "ebe": {}, "moria": 4805}, {"id": 272, "tmima": "Μηχανικών Επιστήμης Υλικών", "sxoli": "ΠΑΝΕΠΙΣΤΗΜΙΟ ΙΩΑΝΝΙΝΩΝ", "extraInfo": null, "tipos": "ΑΕΙ", "poli": "Ιωάννινα", "ebe": {}, "moria": 4800}, {"id": 762, "tmima": "Τεχνολόγων Γεωπόνων", "sxoli": "Τ.Ε.Ι. ΔΥΤΙΚΗΣ ΜΑΚΕΔΟΝΙΑΣ", "extraInfo": "(Δεν υπάρχει στο Μηχανογραφικό του 2022)", "tipos": "ΤΕΙ", "poli": "Φλώρινα", "ebe": {}, "moria": 4798}, {"id": 512, "tmima": "Μηχανικών Ενεργειακής Τεχνολογίας ΤΕ", "sxoli": "Τ.Ε.Ι. ΑΘΗΝΑΣ", "extraInfo": "(Δεν υπάρχει στο Μηχανογραφικό του 2022)", "tipos": "ΤΕΙ", "poli": "Αθήνα", "ebe": {}, "moria": 4774}, {"id": 220, "tmima": "Ηλεκτρολόγων Μηχανικών και Μηχανικών Υπολογιστών", "sxoli": "ΠΑΝΕΠΙΣΤΗΜΙΟ ΘΕΣΣΑΛΙΑΣ", "extraInfo": null, "tipos": "ΑΕΙ", "poli": "Βόλος", "ebe": {}, "moria": 4705}, {"id": 222, "tmima": "Μηχανικών Οικονομίας και Διοίκησης", "sxoli": "ΠΑΝΕΠΙΣΤΗΜΙΟ ΑΙΓΑΙΟΥ", "extraInfo": null, "tipos": "ΑΕΙ", "poli": "Χίος", "ebe": {}, "moria": 4692}, {"id": 701, "tmima": "Κλωστοϋφαντουργών Μηχανικών ΤΕ", "sxoli": "Τ.Ε.Ι. ΠΕΙΡΑΙΑ", "extraInfo": "(Δεν υπάρχει στο Μηχανογραφικό του 2022)", "tipos": "ΤΕΙ", "poli": "Πειραιάς", "ebe": {}, "moria": 4674}, {"id": 221, "tmima": "Ηλεκτρολόγων Μηχανικών και Τεχνολογίας Υπολογιστών", "sxoli": "ΠΑΝΕΠΙΣΤΗΜΙΟ ΠΑΤΡΩΝ", "extraInfo": null, "tipos": "ΑΕΙ", "poli": "Πάτρα", "ebe": {}, "moria": 4658}, {"id": 717, "tmima": "Τεχνολογίας Τροφίμων", "sxoli": "ΑΛΕΞΑΝΔΡΕΙΟ Τ.Ε.Ι. ΘΕΣΣΑΛΟΝΙΚΗΣ", "extraInfo": "(Δεν υπάρχει στο Μηχανογραφικό του 2022)", "tipos": "ΤΕΙ", "poli": "Θεσσαλονίκη", "ebe": {}, "moria": 4622}, {"id": 487, "tmima": "Ηλεκτρολόγων Μηχανικών ΤΕ", "sxoli": "Τ.Ε.Ι. ΔΥΤΙΚΗΣ ΕΛΛΑΔΑΣ", "extraInfo": "(Δεν υπάρχει στο Μηχανογραφικό του 2022)", "tipos": "ΤΕΙ", "poli": "Πάτρα", "ebe": {}, "moria": 4568}, {"id": 451, "tmima": "Πολιτικών Μηχανικών ΤΕ", "sxoli": "Τ.Ε.Ι. ΘΕΣΣΑΛΙΑΣ", "extraInfo": "(Δεν υπάρχει στο Μηχανογραφικό του 2022)", "tipos": "ΤΕΙ", "poli": "Λάρισα", "ebe": {}, "moria": 4538}, {"id": 546, "tmima": "Τεχνολογίας Τροφίμων", "sxoli": "Τ.Ε.Ι. ΙΟΝΙΩΝ ΝΗΣΩΝ", "extraInfo": "(Δεν υπάρχει στο Μηχανογραφικό του 2022)", "tipos": "ΤΕΙ", "poli": "Αργοστόλι", "ebe": {}, "moria": 4512}, {"id": 255, "tmima": "Φυσικής", "sxoli": "ΑΡΙΣΤΟΤΕΛΕΙΟ ΠΑΝΕΠΙΣΤΗΜΙΟ ΘΕΣΣΑΛΟΝΙΚΗΣ (ΑΠΘ)", "extraInfo": null, "tipos": "ΑΕΙ", "poli": "Θεσσαλονίκη", "ebe": {}, "moria": 4508}, {"id": 253, "tmima": "Φυσικής", "sxoli": "ΕΘΝΙΚΟ & ΚΑΠΟΔΙΣΤΡΙΑΚΟ ΠΑΝΕΠΙΣΤΗΜΙΟ ΑΘΗΝΩΝ (ΕΚΠΑ)", "extraInfo": null, "tipos": "ΑΕΙ", "poli": "Αθήνα", "ebe": {}, "moria": 4503}, {"id": 761, "tmima": "Τεχνολόγων Γεωπόνων", "sxoli": "Τ.Ε.Ι. ΘΕΣΣΑΛΙΑΣ", "extraInfo": "(Δεν υπάρχει στο Μηχανογραφικό του 2022)", "tipos": "ΤΕΙ", "poli": "Λάρισα", "ebe": {}, "moria": 4484}, {"id": 714, "tmima": "Μηχανικών Αυτοματισμού ΤΕ", "sxoli": "Τ.Ε.Ι. ΠΕΙΡΑΙΑ", "extraInfo": "(Δεν υπάρχει στο Μηχανογραφικό του 2022)", "tipos": "ΤΕΙ", "poli": "Πειραιάς", "ebe": {}, "moria": 4470}, {"id": 532, "tmima": "Μηχανικών Φυσικών Πόρων και Περιβάλλοντος ΤΕ", "sxoli": "Τ.Ε.Ι. ΚΡΗΤΗΣ", "extraInfo": "(Δεν υπάρχει στο Μηχανογραφικό του 2022)", "tipos": "ΤΕΙ", "poli": "Χανιά", "ebe": {}, "moria": 4460}, {"id": 213, "tmima": "Μηχανολόγων και Αεροναυπηγών Μηχανικών", "sxoli": "ΠΑΝΕΠΙΣΤΗΜΙΟ ΠΑΤΡΩΝ", "extraInfo": null, "tipos": "ΑΕΙ", "poli": "Πάτρα", "ebe": {}, "moria": 4456}, {"id": 711, "tmima": "Μηχανικών Πληροφορικής ΤΕ", "sxoli": "Τ.Ε.Ι. ΑΘΗΝΑΣ", "extraInfo": "(Δεν υπάρχει στο Μηχανογραφικό του 2022)", "tipos": "ΤΕΙ", "poli": "Αθήνα", "ebe": {}, "moria": 4448}, {"id": 505, "tmima": "Ηλεκτρονικών Μηχανικών ΤΕ", "sxoli": "ΑΛΕΞΑΝΔΡΕΙΟ Τ.Ε.Ι. ΘΕΣΣΑΛΟΝΙΚΗΣ", "extraInfo": "(Δεν υπάρχει στο Μηχανογραφικό του 2022)", "tipos": "ΤΕΙ", "poli": "Θεσσαλονίκη", "ebe": {}, "moria": 4430}, {"id": 443, "tmima": "Πολιτικών Μηχανικών ΤΕ / Εισ. Κατεύθυνση (Τμ. Πολ. Μηχ/κών ΤΕ & Μηχ/κών Τοπογραφίας & Γεωπληρ/ικής ΤΕ)", "sxoli": "Τ.Ε.Ι. ΑΘΗΝΑΣ", "extraInfo": "(Δεν υπάρχει στο Μηχανογραφικό του 2022)", "tipos": "ΤΕΙ", "poli": "Αθήνα", "ebe": {}, "moria": 4406}, {"id": 644, "tmima": "Μηχανικών Μουσικής Τεχνολογίας και Ακουστικής ΤΕ", "sxoli": "Τ.Ε.Ι. ΚΡΗΤΗΣ", "extraInfo": "(Δεν υπάρχει στο Μηχανογραφικό του 2022)", "tipos": "ΤΕΙ", "poli": "Ρέθυμνο", "ebe": {}, "moria": 4378}, {"id": 271, "tmima": "Διαχείρισης Περιβάλλοντος και Φυσικών Πόρων", "sxoli": "ΠΑΝΕΠΙΣΤΗΜΙΟ ΠΑΤΡΩΝ", "extraInfo": "(Δεν υπάρχει στο Μηχανογραφικό του 2022)", "tipos": "ΑΕΙ", "poli": "Αγρίνιο", "ebe": {}, "moria": 4362}, {"id": 479, "tmima": "Μηχανολόγων Μηχανικών ΤΕ", "sxoli": "Τ.Ε.Ι. ΣΤΕΡΕΑΣ ΕΛΛΑΔΑΣ", "extraInfo": "(Δεν υπάρχει στο Μηχανογραφικό του 2022)", "tipos": "ΤΕΙ", "poli": "Χαλκίδα", "ebe": {}, "moria": 4356}, {"id": 465, "tmima": "Μηχανολόγων Μηχανικών ΤΕ", "sxoli": "Τ.Ε.Ι. ΔΥΤΙΚΗΣ ΕΛΛΑΔΑΣ", "extraInfo": "(Δεν υπάρχει στο Μηχανογραφικό του 2022)", "tipos": "ΤΕΙ", "poli": "Πάτρα", "ebe": {}, "moria": 4356}, {"id": 503, "tmima": "Ηλεκτρονικών Μηχανικών ΤΕ", "sxoli": "Τ.Ε.Ι. ΠΕΙΡΑΙΑ", "extraInfo": "(Δεν υπάρχει στο Μηχανογραφικό του 2022)", "tipos": "ΤΕΙ", "poli": "Πειραιάς", "ebe": {}, "moria": 4354}, {"id": 243, "tmima": "Μαθηματικών", "sxoli": "ΕΘΝΙΚΟ & ΚΑΠΟΔΙΣΤΡΙΑΚΟ ΠΑΝΕΠΙΣΤΗΜΙΟ ΑΘΗΝΩΝ (ΕΚΠΑ)", "extraInfo": null, "tipos": "ΑΕΙ", "poli": "Αθήνα", "ebe": {}, "moria": 4354}, {"id": 491, "tmima": "Ηλεκτρολόγων Μηχανικών ΤΕ", "sxoli": "Τ.Ε.Ι. ΚΡΗΤΗΣ", "extraInfo": "(Δεν υπάρχει στο Μηχανογραφικό του 2022)", "tipos": "ΤΕΙ", "poli": "Ηράκλειο", "ebe": {}, "moria": 4344}, {"id": 265, "tmima": "Χημείας", "sxoli": "ΑΡΙΣΤΟΤΕΛΕΙΟ ΠΑΝΕΠΙΣΤΗΜΙΟ ΘΕΣΣΑΛΟΝΙΚΗΣ (ΑΠΘ)", "extraInfo": null, "tipos": "ΑΕΙ", "poli": "Θεσσαλονίκη", "ebe": {}, "moria": 4289}, {"id": 288, "tmima": "Επιστήμης των Υλικών", "sxoli": "ΠΑΝΕΠΙΣΤΗΜΙΟ ΠΑΤΡΩΝ", "extraInfo": null, "tipos": "ΑΕΙ", "poli": "Πάτρα", "ebe": {}, "moria": 4267}, {"id": 768, "tmima": "Πολιτικών Μηχανικών ΤΕ", "sxoli": "Τ.Ε.Ι. ΔΥΤΙΚΗΣ ΕΛΛΑΔΑΣ", "extraInfo": "(Δεν υπάρχει στο Μηχανογραφικό του 2022)", "tipos": "ΤΕΙ", "poli": "Πάτρα", "ebe": {}, "moria": 4214}, {"id": 269, "tmima": "Χημείας", "sxoli": "ΠΑΝΕΠΙΣΤΗΜΙΟ ΙΩΑΝΝΙΝΩΝ", "extraInfo": null, "tipos": "ΑΕΙ", "poli": "Ιωάννινα", "ebe": {}, "moria": 4190}, {"id": 447, "tmima": "Πολιτικών Μηχανικών ΤΕ", "sxoli": "ΑΛΕΞΑΝΔΡΕΙΟ Τ.Ε.Ι. ΘΕΣΣΑΛΟΝΙΚΗΣ", "extraInfo": "(Δεν υπάρχει στο Μηχανογραφικό του 2022)", "tipos": "ΤΕΙ", "poli": "Θεσσαλονίκη", "ebe": {}, "moria": 4182}, {"id": 509, "tmima": "Μηχανικών Τοπογραφίας & Γεωπληροφορικής ΤΕ / Εισ. Κατεύθυνση (Τμ. Πολ. Μηχ/κών ΤΕ & Μηχ/κών Τοπογραφίας & Γεωπληρ/ικής ΤΕ)", "sxoli": "Τ.Ε.Ι. ΑΘΗΝΑΣ", "extraInfo": "(Δεν υπάρχει στο Μηχανογραφικό του 2022)", "tipos": "ΤΕΙ", "poli": "Αθήνα", "ebe": {}, "moria": 4171}, {"id": 248, "tmima": "Μαθηματικών και Εφαρμοσμένων Μαθηματικών - Εφαρμοσμένων Μαθηματικών", "sxoli": "ΠΑΝΕΠΙΣΤΗΜΙΟ ΚΡΗΤΗΣ", "extraInfo": null, "tipos": "ΑΕΙ", "poli": "Ηράκλειο", "ebe": {}, "moria": 4121}, {"id": 760, "tmima": "Τεχνολόγων Γεωπόνων", "sxoli": "Τ.Ε.Ι. ΠΕΛΟΠΟΝΝΗΣΟΥ", "extraInfo": "(Δεν υπάρχει στο Μηχανογραφικό του 2022)", "tipos": "ΤΕΙ", "poli": "Καλαμάτα", "ebe": {}, "moria": 4048}, {"id": 515, "tmima": "Τεχνολογίας Τροφίμων", "sxoli": "Τ.Ε.Ι. ΠΕΛΟΠΟΝΝΗΣΟΥ", "extraInfo": "(Δεν υπάρχει στο Μηχανογραφικό του 2022)", "tipos": "ΤΕΙ", "poli": "Καλαμάτα", "ebe": {}, "moria": 4034}, {"id": 331, "tmima": "Ηλεκτρολόγων Μηχανικών και Μηχανικών Υπολογιστών", "sxoli": "ΠΟΛΥΤΕΧΝΕΙΟ ΚΡΗΤΗΣ", "extraInfo": null, "tipos": "ΑΕΙ", "poli": "Χανιά", "ebe": {}, "moria": 3972}, {"id": 495, "tmima": "Ηλεκτρολόγων Μηχανικών ΤΕ", "sxoli": "Τ.Ε.Ι. ΔΥΤΙΚΗΣ ΜΑΚΕΔΟΝΙΑΣ", "extraInfo": "(Δεν υπάρχει στο Μηχανογραφικό του 2022)", "tipos": "ΤΕΙ", "poli": "Κοζάνη", "ebe": {}, "moria": 3936}, {"id": 737, "tmima": "Μηχανικών Τεχνολογίας Αεροσκαφών ΤΕ", "sxoli": "Τ.Ε.Ι. ΣΤΕΡΕΑΣ ΕΛΛΑΔΑΣ", "extraInfo": "(Δεν υπάρχει στο Μηχανογραφικό του 2022)", "tipos": "ΤΕΙ", "poli": "Χαλκίδα", "ebe": {}, "moria": 3928}, {"id": 713, "tmima": "Μηχανικών Ηλεκτρονικών Υπολογιστικών Συστημάτων ΤΕ", "sxoli": "Τ.Ε.Ι. ΠΕΙΡΑΙΑ", "extraInfo": "(Δεν υπάρχει στο Μηχανογραφικό του 2022)", "tipos": "ΤΕΙ", "poli": "Πειραιάς", "ebe": {}, "moria": 3864}, {"id": 310, "tmima": "Γεωγραφίας", "sxoli": "ΠΑΝΕΠΙΣΤΗΜΙΟ ΑΙΓΑΙΟΥ", "extraInfo": null, "tipos": "ΑΕΙ", "poli": "Μυτιλήνη", "ebe": {}, "moria": 3861}, {"id": 698, "tmima": "Τεχνολόγων Περιβάλλοντος ΤΕ - Τεχνολογιών Φυσικού Περιβάλλοντος ΤΕ", "sxoli": "Τ.Ε.Ι. ΙΟΝΙΩΝ ΝΗΣΩΝ", "extraInfo": "(Δεν υπάρχει στο Μηχανογραφικό του 2022)", "tipos": "ΤΕΙ", "poli": "Ζάκυνθος", "ebe": {}, "moria": 3856}, {"id": 507, "tmima": "Εκπαιδευτικών Ηλεκτρολόγων Μηχανικών και Εκπαιδευτικών Ηλεκτρονικών Μηχανικών - Εκπαιδευτικών Ηλεκτρονικών Μηχανικών", "sxoli": "ΑΝΩΤΑΤΗ ΣΧΟΛΗ ΠΑΙΔΑΓΩΓΙΚΗΣ & ΤΕΧΝΟΛΟΓΙΚΗΣ ΕΚΠΑΙΔΕΥΣΗΣ (ΑΣΠΑΙΤΕ)", "extraInfo": null, "tipos": "ΑΣΠΑΙΤΕ", "poli": "Αθήνα", "ebe": {}, "moria": 3758}, {"id": 506, "tmima": "Μηχανικών Πληροφορικής ΤΕ", "sxoli": "Τ.Ε.Ι. ΣΤΕΡΕΑΣ ΕΛΛΑΔΑΣ", "extraInfo": "(Δεν υπάρχει στο Μηχανογραφικό του 2022)", "tipos": "ΤΕΙ", "poli": "Λαμία", "ebe": {}, "moria": 3726}, {"id": 249, "tmima": "Μαθηματικών", "sxoli": "ΠΑΝΕΠΙΣΤΗΜΙΟ ΙΩΑΝΝΙΝΩΝ", "extraInfo": null, "tipos": "ΑΕΙ", "poli": "Ιωάννινα", "ebe": {}, "moria": 3670}, {"id": 318, "tmima": "Στατιστικής και Ασφαλιστικής Επιστήμης", "sxoli": "ΠΑΝΕΠΙΣΤΗΜΙΟ ΠΕΙΡΑΙΑ", "extraInfo": null, "tipos": "ΑΕΙ", "poli": "Πειραιάς", "ebe": {}, "moria": 3652}, {"id": 471, "tmima": "Μηχανικών Τεχνολογίας Πετρελαίου και Φυσικού Αερίου ΤΕ και Μηχανολόγων Μηχανικών ΤΕ - Μηχανολόγων Μηχανικών ΤΕ", "sxoli": "Τ.Ε.Ι. ΑΝΑΤΟΛΙΚΗΣ ΜΑΚΕΔΟΝΙΑΣ & ΘΡΑΚΗΣ", "extraInfo": "(Δεν υπάρχει στο Μηχανογραφικό του 2022)", "tipos": "ΤΕΙ", "poli": "Καβάλα", "ebe": {}, "moria": 3644}, {"id": 200, "tmima": "Επιστήμης και Τεχνολογίας Υλικών", "sxoli": "ΠΑΝΕΠΙΣΤΗΜΙΟ ΚΡΗΤΗΣ", "extraInfo": null, "tipos": "ΑΕΙ", "poli": "Ηράκλειο", "ebe": {}, "moria": 3632}, {"id": 721, "tmima": "Μηχανικών Περιβάλλοντος και Μηχανικών Αντιρρύπανσης ΤΕ - Μηχανικών Γεωτεχνολογίας Περιβάλλοντος ΤΕ", "sxoli": "Τ.Ε.Ι. ΔΥΤΙΚΗΣ ΜΑΚΕΔΟΝΙΑΣ", "extraInfo": "(Δεν υπάρχει στο Μηχανογραφικό του 2022)", "tipos": "ΤΕΙ", "poli": "Κοζάνη", "ebe": {}, "moria": 3522}, {"id": 550, "tmima": "Δασοπονίας και Διαχείρισης Φυσικού Περιβάλλοντος", "sxoli": "Τ.Ε.Ι. ΑΝΑΤΟΛΙΚΗΣ ΜΑΚΕΔΟΝΙΑΣ & ΘΡΑΚΗΣ", "extraInfo": "(Δεν υπάρχει στο Μηχανογραφικό του 2022)", "tipos": "ΤΕΙ", "poli": "Δράμα", "ebe": {}, "moria": 3520}, {"id": 230, "tmima": "Μηχανικών Παραγωγής και Διοίκησης", "sxoli": "ΠΟΛΥΤΕΧΝΕΙΟ ΚΡΗΤΗΣ", "extraInfo": null, "tipos": "ΑΕΙ", "poli": "Χανιά", "ebe": {}, "moria": 3378}, {"id": 242, "tmima": "Μηχανικών Ορυκτών Πόρων", "sxoli": "ΠΟΛΥΤΕΧΝΕΙΟ ΚΡΗΤΗΣ", "extraInfo": null, "tipos": "ΑΕΙ", "poli": "Χανιά", "ebe": {}, "moria": 3369}, {"id": 366, "tmima": "Πληροφορικής", "sxoli": "ΙΟΝΙΟ ΠΑΝΕΠΙΣΤΗΜΙΟ", "extraInfo": null, "tipos": "ΑΕΙ", "poli": "Κέρκυρα", "ebe": {}, "moria": 3347}, {"id": 251, "tmima": "Μαθηματικών και Εφαρμοσμένων Μαθηματικών - Μαθηματικών", "sxoli": "ΠΑΝΕΠΙΣΤΗΜΙΟ ΚΡΗΤΗΣ", "extraInfo": null, "tipos": "ΑΕΙ", "poli": "Ηράκλειο", "ebe": {}, "moria": 3332}, {"id": 497, "tmima": "Εκπαιδευτικών Ηλεκτρολόγων Μηχανικών και Εκπαιδευτικών Ηλεκτρονικών Μηχανικών - Εκπαιδευτικών Ηλεκτρολόγων Μηχανικών", "sxoli": "ΑΝΩΤΑΤΗ ΣΧΟΛΗ ΠΑΙΔΑΓΩΓΙΚΗΣ & ΤΕΧΝΟΛΟΓΙΚΗΣ ΕΚΠΑΙΔΕΥΣΗΣ (ΑΣΠΑΙΤΕ)", "extraInfo": null, "tipos": "ΑΣΠΑΙΤΕ", "poli": "Αθήνα", "ebe": {}, "moria": 3327}, {"id": 710, "tmima": "Μηχανικών Πληροφορικής ΤΕ", "sxoli": "Τ.Ε.Ι. ΗΠΕΙΡΟΥ", "extraInfo": "(Δεν υπάρχει στο Μηχανογραφικό του 2022)", "tipos": "ΤΕΙ", "poli": "Άρτα", "ebe": {}, "moria": 3319}, {"id": 712, "tmima": "Μηχανικών Πληροφορικής ΤΕ", "sxoli": "ΑΛΕΞΑΝΔΡΕΙΟ Τ.Ε.Ι. ΘΕΣΣΑΛΟΝΙΚΗΣ", "extraInfo": "(Δεν υπάρχει στο Μηχανογραφικό του 2022)", "tipos": "ΤΕΙ", "poli": "Θεσσαλονίκη", "ebe": {}, "moria": 3302}, {"id": 344, "tmima": "Μηχανικών Πληροφοριακών και Επικοινωνιακών Συστημάτων", "sxoli": "ΠΑΝΕΠΙΣΤΗΜΙΟ ΑΙΓΑΙΟΥ", "extraInfo": null, "tipos": "ΑΕΙ", "poli": "Σάμος", "ebe": {}, "moria": 3254}, {"id": 99, "tmima": "Πληροφορικής και Τηλεπικοινωνιών", "sxoli": "ΠΑΝΕΠΙΣΤΗΜΙΟ ΘΕΣΣΑΛΙΑΣ", "extraInfo": null, "tipos": "ΑΕΙ", "poli": "Λαμία", "ebe": {}, "moria": 3246}, {"id": 493, "tmima": "Ηλεκτρολόγων Μηχανικών ΤΕ", "sxoli": "Τ.Ε.Ι. ΑΝΑΤΟΛΙΚΗΣ ΜΑΚΕΔΟΝΙΑΣ & ΘΡΑΚΗΣ", "extraInfo": "(Δεν υπάρχει στο Μηχανογραφικό του 2022)", "tipos": "ΤΕΙ", "poli": "Καβάλα", "ebe": {}, "moria": 3234}, {"id": 98, "tmima": "Πληροφορικής και Τηλεπικοινωνιών", "sxoli": "ΠΑΝΕΠΙΣΤΗΜΙΟ ΠΕΛΟΠΟΝΝΗΣΟΥ", "extraInfo": null, "tipos": "ΑΕΙ", "poli": "Τρίπολη", "ebe": {}, "moria": 3182}, {"id": 215, "tmima": "Μηχανικών Ηλεκτρονικών Υπολογιστών και Πληροφορικής", "sxoli": "ΠΑΝΕΠΙΣΤΗΜΙΟ ΠΑΤΡΩΝ", "extraInfo": null, "tipos": "ΑΕΙ", "poli": "Πάτρα", "ebe": {}, "moria": 3106}, {"id": 739, "tmima": "Τεχνολογίας Τροφίμων", "sxoli": "Τ.Ε.Ι. ΘΕΣΣΑΛΙΑΣ", "extraInfo": "(Δεν υπάρχει στο Μηχανογραφικό του 2022)", "tipos": "ΤΕΙ", "poli": "Καρδίτσα", "ebe": {}, "moria": 3072}, {"id": 513, "tmima": "Μηχανικών Τεχνολογίας Πετρελαίου και Φυσικού Αερίου ΤΕ και Μηχανολόγων Μηχανικών ΤΕ - Μηχανικών Τεχνολογίας Πετρελαίου και Φυσικού Αερίου ΤΕ", "sxoli": "Τ.Ε.Ι. ΑΝΑΤΟΛΙΚΗΣ ΜΑΚΕΔΟΝΙΑΣ & ΘΡΑΚΗΣ", "extraInfo": "(Δεν υπάρχει στο Μηχανογραφικό του 2022)", "tipos": "ΤΕΙ", "poli": "Καβάλα", "ebe": {}, "moria": 3052}, {"id": 467, "tmima": "Μηχανολόγων Μηχανικών ΤΕ", "sxoli": "Τ.Ε.Ι. ΘΕΣΣΑΛΙΑΣ", "extraInfo": "(Δεν υπάρχει στο Μηχανογραφικό του 2022)", "tipos": "ΤΕΙ", "poli": "Λάρισα", "ebe": {}, "moria": 3046}, {"id": 735, "tmima": "Μηχανικών Πληροφορικής ΤΕ", "sxoli": "Τ.Ε.Ι. ΔΥΤΙΚΗΣ ΜΑΚΕΔΟΝΙΑΣ", "extraInfo": "(Δεν υπάρχει στο Μηχανογραφικό του 2022)", "tipos": "ΤΕΙ", "poli": "Καστοριά", "ebe": {}, "moria": 2946}, {"id": 709, "tmima": "Ηλεκτρονικών Μηχανικών ΤΕ", "sxoli": "Τ.Ε.Ι. ΚΡΗΤΗΣ", "extraInfo": "(Δεν υπάρχει στο Μηχανογραφικό του 2022)", "tipos": "ΤΕΙ", "poli": "Χανιά", "ebe": {}, "moria": 2942}, {"id": 724, "tmima": "Μηχανικών Πληροφορικής ΤΕ", "sxoli": "Τ.Ε.Ι. ΑΝΑΤΟΛΙΚΗΣ ΜΑΚΕΔΟΝΙΑΣ & ΘΡΑΚΗΣ", "extraInfo": "(Δεν υπάρχει στο Μηχανογραφικό του 2022)", "tipos": "ΤΕΙ", "poli": "Καβάλα", "ebe": {}, "moria": 2918}, {"id": 555, "tmima": "Τεχνολογίας Αλιείας - Υδατοκαλλιεργειών", "sxoli": "Τ.Ε.Ι. ΔΥΤΙΚΗΣ ΕΛΛΑΔΑΣ", "extraInfo": "(Δεν υπάρχει στο Μηχανογραφικό του 2022)", "tipos": "ΤΕΙ", "poli": "Μεσολόγγι", "ebe": {}, "moria": 2912}, {"id": 736, "tmima": "Μηχανικών Πληροφορικής ΤΕ", "sxoli": "Τ.Ε.Ι. ΔΥΤΙΚΗΣ ΕΛΛΑΔΑΣ", "extraInfo": "(Δεν υπάρχει στο Μηχανογραφικό του 2022)", "tipos": "ΤΕΙ", "poli": "Ναύπακτος", "ebe": {}, "moria": 2906}, {"id": 725, "tmima": "Μηχανικών Πληροφορικής ΤΕ", "sxoli": "Τ.Ε.Ι. ΚΡΗΤΗΣ", "extraInfo": "(Δεν υπάρχει στο Μηχανογραφικό του 2022)", "tipos": "ΤΕΙ", "poli": "Ηράκλειο", "ebe": {}, "moria": 2894}, {"id": 499, "tmima": "Ηλεκτρολόγων Μηχανικών ΤΕ", "sxoli": "Τ.Ε.Ι. ΣΤΕΡΕΑΣ ΕΛΛΑΔΑΣ", "extraInfo": "(Δεν υπάρχει στο Μηχανογραφικό του 2022)", "tipos": "ΤΕΙ", "poli": "Χαλκίδα", "ebe": {}, "moria": 2843}, {"id": 239, "tmima": "Χημικών Μηχανικών", "sxoli": "ΠΑΝΕΠΙΣΤΗΜΙΟ ΠΑΤΡΩΝ", "extraInfo": null, "tipos": "ΑΕΙ", "poli": "Πάτρα", "ebe": {}, "moria": 2810}, {"id": 722, "tmima": "Μηχανικών Αυτοματισμού ΤΕ", "sxoli": "Τ.Ε.Ι. ΣΤΕΡΕΑΣ ΕΛΛΑΔΑΣ", "extraInfo": "(Δεν υπάρχει στο Μηχανογραφικό του 2022)", "tipos": "ΤΕΙ", "poli": "Χαλκίδα", "ebe": {}, "moria": 2632}, {"id": 529, "tmima": "Μηχανικών Πληροφορικής ΤΕ", "sxoli": "Τ.Ε.Ι. ΠΕΛΟΠΟΝΝΗΣΟΥ", "extraInfo": "(Δεν υπάρχει στο Μηχανογραφικό του 2022)", "tipos": "ΤΕΙ", "poli": "Σπάρτη", "ebe": {}, "moria": 2622}, {"id": 723, "tmima": "Μηχανικών Πληροφορικής ΤΕ", "sxoli": "Τ.Ε.Ι. ΘΕΣΣΑΛΙΑΣ", "extraInfo": "(Δεν υπάρχει στο Μηχανογραφικό του 2022)", "tipos": "ΤΕΙ", "poli": "Λάρισα", "ebe": {}, "moria": 2590}, {"id": 489, "tmima": "Ηλεκτρολόγων Μηχανικών ΤΕ", "sxoli": "Τ.Ε.Ι. ΘΕΣΣΑΛΙΑΣ", "extraInfo": "(Δεν υπάρχει στο Μηχανογραφικό του 2022)", "tipos": "ΤΕΙ", "poli": "Λάρισα", "ebe": {}, "moria": 2588}, {"id": 247, "tmima": "Μαθηματικών", "sxoli": "ΠΑΝΕΠΙΣΤΗΜΙΟ ΠΑΤΡΩΝ", "extraInfo": null, "tipos": "ΑΕΙ", "poli": "Πάτρα", "ebe": {}, "moria": 2546}, {"id": 224, "tmima": "Μηχανικών Παραγωγής και Διοίκησης", "sxoli": "ΔΗΜΟΚΡΙΤΕΙΟ ΠΑΝΕΠΙΣΤΗΜΙΟ ΘΡΑΚΗΣ (ΔΠΘ)", "extraInfo": null, "tipos": "ΑΕΙ", "poli": "Ξάνθη", "ebe": {}, "moria": 2496}, {"id": 551, "tmima": "Δασοπονίας και Διαχείρισης Φυσικού Περιβάλλοντος", "sxoli": "Τ.Ε.Ι. ΣΤΕΡΕΑΣ ΕΛΛΑΔΑΣ", "extraInfo": "(Δεν υπάρχει στο Μηχανογραφικό του 2022)", "tipos": "ΤΕΙ", "poli": "Καρπενήσι", "ebe": {}, "moria": 2450}, {"id": 592, "tmima": "Μηχανολόγων Μηχανικών και Βιομηχανικού Σχεδιασμού ΤΕ -Βιομηχανικού Σχεδιασμού ΤΕ", "sxoli": "Τ.Ε.Ι. ΔΥΤΙΚΗΣ ΜΑΚΕΔΟΝΙΑΣ", "extraInfo": "(Δεν υπάρχει στο Μηχανογραφικό του 2022)", "tipos": "ΤΕΙ", "poli": "Κοζάνη", "ebe": {}, "moria": 2404}, {"id": 473, "tmima": "Μηχανολόγων Μηχανικών και Βιομηχανικού Σχεδιασμού ΤΕ -Μηχανολόγων Μηχανικών ΤΕ", "sxoli": "Τ.Ε.Ι. ΔΥΤΙΚΗΣ ΜΑΚΕΔΟΝΙΑΣ", "extraInfo": "(Δεν υπάρχει στο Μηχανογραφικό του 2022)", "tipos": "ΤΕΙ", "poli": "Κοζάνη", "ebe": {}, "moria": 2374}, {"id": 703, "tmima": "Σχεδιασμού και Τεχνολογίας Ένδυσης", "sxoli": "Τ.Ε.Ι. ΚΕΝΤΡΙΚΗΣ ΜΑΚΕΔΟΝΙΑΣ", "extraInfo": "(Δεν υπάρχει στο Μηχανογραφικό του 2022)", "tipos": "ΤΕΙ", "poli": "Κιλκίς", "ebe": {}, "moria": 2192}, {"id": 510, "tmima": "Πολιτικών Μηχανικών ΤΕ και Μηχανικών Τοπογραφίας και Γεωπληροφορικής ΤΕ - Μηχανικών Τοπογραφίας και Γεωπληροφορικής ΤΕ", "sxoli": "Τ.Ε.Ι. ΚΕΝΤΡΙΚΗΣ ΜΑΚΕΔΟΝΙΑΣ", "extraInfo": "(Δεν υπάρχει στο Μηχανογραφικό του 2022)", "tipos": "ΤΕΙ", "poli": "Σέρρες", "ebe": {}, "moria": 2156}, {"id": 514, "tmima": "Μηχανικών Περιβάλλοντος και Μηχανικών Αντιρρύπανσης ΤΕ - Μηχανικων Αντιρρύπανσης ΤΕ", "sxoli": "Τ.Ε.Ι. ΔΥΤΙΚΗΣ ΜΑΚΕΔΟΝΙΑΣ", "extraInfo": "(Δεν υπάρχει στο Μηχανογραφικό του 2022)", "tipos": "ΤΕΙ", "poli": "Κοζάνη", "ebe": {}, "moria": 2126}, {"id": 259, "tmima": "Φυσικής", "sxoli": "ΠΑΝΕΠΙΣΤΗΜΙΟ ΙΩΑΝΝΙΝΩΝ", "extraInfo": null, "tipos": "ΑΕΙ", "poli": "Ιωάννινα", "ebe": {}, "moria": 2052}, {"id": 705, "tmima": "Ηλεκτρονικών Μηχανικών ΤΕ", "sxoli": "Τ.Ε.Ι. ΣΤΕΡΕΑΣ ΕΛΛΑΔΑΣ", "extraInfo": "(Δεν υπάρχει στο Μηχανογραφικό του 2022)", "tipos": "ΤΕΙ", "poli": "Λαμία", "ebe": {}, "moria": 2044}, {"id": 727, "tmima": "Μηχανικών Πληροφορικής ΤΕ", "sxoli": "Τ.Ε.Ι. ΚΕΝΤΡΙΚΗΣ ΜΑΚΕΔΟΝΙΑΣ", "extraInfo": "(Δεν υπάρχει στο Μηχανογραφικό του 2022)", "tipos": "ΤΕΙ", "poli": "Σέρρες", "ebe": {}, "moria": 2000}, {"id": 475, "tmima": "Μηχανολόγων Μηχανικών ΤΕ", "sxoli": "Τ.Ε.Ι. ΚΕΝΤΡΙΚΗΣ ΜΑΚΕΔΟΝΙΑΣ", "extraInfo": "(Δεν υπάρχει στο Μηχανογραφικό του 2022)", "tipos": "ΤΕΙ", "poli": "Σέρρες", "ebe": {}, "moria": 1780}, {"id": 257, "tmima": "Φυσικής", "sxoli": "ΠΑΝΕΠΙΣΤΗΜΙΟ ΠΑΤΡΩΝ", "extraInfo": null, "tipos": "ΑΕΙ", "poli": "Πάτρα", "ebe": {}, "moria": 216}]